Spruce_lang-0.2.0-py2.7-nspkg.pth
spruce/lang/__init__.py
spruce/lang/_misc.py
Spruce_lang-0.2.0.dist-info/METADATA
Spruce_lang-0.2.0.dist-info/entry_points.txt
Spruce_lang-0.2.0.dist-info/RECORD
Spruce_lang-0.2.0.dist-info/top_level.txt
Spruce_lang-0.2.0.dist-info/namespace_packages.txt
Spruce_lang-0.2.0.dist-info/WHEEL
Spruce_lang-0.2.0.dist-info/metadata.json
Spruce_lang-0.2.0.dist-info/DESCRIPTION.rst
