Metadata-Version: 2.0
Name: Spruce-lang
Version: 0.2.0
Summary: Python language extensions
Home-page: UNKNOWN
Author: Ivan D Vasin
Author-email: nisavid@gmail.com
License: GNU LESSER GENERAL PUBLIC LICENSE
